setup.cfg
setup.py
tessfpe/__init__.py
tessfpe/simulator.py
tessfpe.egg-info/PKG-INFO
tessfpe.egg-info/SOURCES.txt
tessfpe.egg-info/dependency_links.txt
tessfpe.egg-info/requires.txt
tessfpe.egg-info/top_level.txt
tessfpe/data/__init__.py
tessfpe/data/data.py
tessfpe/data/housekeeping_channels.py
tessfpe/data/operating_parameters.py
tessfpe/data/files/BiasGroup.tsv
tessfpe/data/files/ClockDriverGroup.tsv
tessfpe/data/files/HKmap.tsv
tessfpe/data/files/HeaterGroup.tsv
tessfpe/data/files/InterfaceGroup.tsv
tessfpe/data/files/ThermalGroup.tsv
tessfpe/data/files/default_program.fpe
tessfpe/dhu/__init__.py
tessfpe/dhu/binary_files.py
tessfpe/dhu/fpe.py
tessfpe/dhu/fpesocketconnection.py
tessfpe/dhu/MemFiles/CLV.bin
tessfpe/dhu/MemFiles/FPE_Wrapper.bin
tessfpe/dhu/MemFiles/Hsk.bin
tessfpe/dhu/MemFiles/Prg.bin
tessfpe/dhu/MemFiles/Reg.bin
tessfpe/dhu/MemFiles/Seq.bin
tessfpe/sequencer_dsl/SequencerDSLParser.py
tessfpe/sequencer_dsl/__init__.py
tessfpe/sequencer_dsl/ast.py
tessfpe/sequencer_dsl/parse.py
tessfpe/sequencer_dsl/program.py
tessfpe/sequencer_dsl/sequence.py