Metadata-Version: 1.1
Name: tessfpe
Version: 6.1.12.dev9
Summary: Software to accompany the Focal Plane Electronics (FPE) for the Transiting Exoplanet Survey Satellite (TESS)
Home-page: https://github.com/TESScience/FPE
Author: John Doty
Author-email: jpd@noqsi.com
License: UNKNOWN
Download-URL: https://github.com/TESScience/FPE/tarball/6.1.12.dev9
Platform: UNKNOWN
